zahner_analysis/__init__.py
zahner_analysis/analysis_tools/__init__.py
zahner_analysis/analysis_tools/analysis_connection.py
zahner_analysis/analysis_tools/eis_fitting.py
zahner_analysis/analysis_tools/error.py
zahner_analysis/analysis_tools/setup_compensation.py
zahner_analysis/file_export/__init__.py
zahner_analysis/file_export/ism_export.py
zahner_analysis/file_import/__init__.py
zahner_analysis/file_import/impedance_model_import.py
zahner_analysis/file_import/isc_import.py
zahner_analysis/file_import/ism_import.py
zahner_analysis/file_import/iss_import.py
zahner_analysis/file_import/isw_import.py
zahner_analysis/file_import/seqtxt_import.py
zahner_analysis/file_import/thales_file_utils.py
zahner_analysis/plotting/__init__.py
zahner_analysis/plotting/impedance_plot.py
zahner_analysis-1.1.5.dist-info/LICENSE
zahner_analysis-1.1.5.dist-info/METADATA
zahner_analysis-1.1.5.dist-info/WHEEL
zahner_analysis-1.1.5.dist-info/top_level.txt
zahner_analysis-1.1.5.dist-info/RECORD
