Metadata-Version: 2.1
Name: zahner_analysis
Version: 1.1.5
Summary: Python package for the analysis of electrochemical impedance spectra.
Author-email: Maximilian Krapp <maximilian.krapp@zahner.de>
License: MIT License
Project-URL: Documentation, https://doc.zahner.de/zahner_analysis
Project-URL: Examples, https://github.com/Zahner-elektrik/Zahner-Analysis-Python/tree/main/Examples
Project-URL: Source Code, https://github.com/Zahner-elektrik/Zahner-Analysis-Python
Project-URL: Bug Tracker, https://github.com/Zahner-elektrik/Zahner-Analysis-Python/issues
Project-URL: Homepage, https://zahner.de/
Keywords: potentiostat,electrochemistry,chemistry,eis,cyclic voltammetry,fuel-cell,battery
Classifier: Development Status :: 5 - Production/Stable
Classifier: Intended Audience :: Developers
Classifier: Intended Audience :: Science/Research
Classifier: Intended Audience :: Education
Classifier: Intended Audience :: Manufacturing
Classifier: Topic :: Scientific/Engineering
Classifier: Topic :: Scientific/Engineering :: Chemistry
Classifier: Topic :: Scientific/Engineering :: Physics
Classifier: Programming Language :: Python :: 3.9
Classifier: Programming Language :: Python :: 3.10
Classifier: Programming Language :: Python :: 3.11
Classifier: Programming Language :: Python :: 3.12
Classifier: Programming Language :: Python :: 3.13
Classifier: License :: OSI Approved :: MIT License
Classifier: Operating System :: OS Independent
Requires-Python: >=3.9
License-File: LICENSE
Requires-Dist: numpy
Requires-Dist: matplotlib
Requires-Dist: requests
Requires-Dist: scipy
